yt/__init__.py
yt/_typing.py
yt/_version.py
yt/api.py
yt/arraytypes.py
yt/config.py
yt/default.mplstyle
yt/exthook.py
yt/funcs.py
yt/loaders.py
yt/py.typed
yt/sample_data_registry.json
yt/startup_tasks.py
yt/testing.py
yt/_maintenance/__init__.py
yt/_maintenance/backports.py
yt/_maintenance/deprecation.py
yt/_maintenance/ipython_compat.py
yt/_maintenance/numpy2_compat.py
yt/analysis_modules/__init__.py
yt/analysis_modules/absorption_spectrum/__init__.py
yt/analysis_modules/absorption_spectrum/api.py
yt/analysis_modules/cosmological_observation/__init__.py
yt/analysis_modules/cosmological_observation/api.py
yt/analysis_modules/halo_analysis/__init__.py
yt/analysis_modules/halo_analysis/api.py
yt/analysis_modules/halo_finding/__init__.py
yt/analysis_modules/halo_finding/api.py
yt/analysis_modules/halo_mass_function/__init__.py
yt/analysis_modules/halo_mass_function/api.py
yt/analysis_modules/level_sets/__init__.py
yt/analysis_modules/level_sets/api.py
yt/analysis_modules/particle_trajectories/__init__.py
yt/analysis_modules/particle_trajectories/api.py
yt/analysis_modules/photon_simulator/__init__.py
yt/analysis_modules/photon_simulator/api.py
yt/analysis_modules/ppv_cube/__init__.py
yt/analysis_modules/ppv_cube/api.py
yt/analysis_modules/radmc3d_export/__init__.py
yt/analysis_modules/radmc3d_export/api.py
yt/analysis_modules/spectral_integrator/__init__.py
yt/analysis_modules/spectral_integrator/api.py
yt/analysis_modules/star_analysis/__init__.py
yt/analysis_modules/star_analysis/api.py
yt/analysis_modules/sunrise_export/__init__.py
yt/analysis_modules/sunrise_export/api.py
yt/analysis_modules/sunyaev_zeldovich/__init__.py
yt/analysis_modules/sunyaev_zeldovich/api.py
yt/analysis_modules/two_point_functions/__init__.py
yt/analysis_modules/two_point_functions/api.py
yt/data_objects/__init__.py
yt/data_objects/analyzer_objects.py
yt/data_objects/api.py
yt/data_objects/construction_data_containers.py
yt-4.4.1.dist-info/METADATA
yt-4.4.1.dist-info/WHEEL
yt-4.4.1.dist-info/entry_points.txt
yt-4.4.1.dist-info/top_level.txt
yt-4.4.1.dist-info/RECORD
yt-4.4.1.dist-info/licenses/COPYING.txt
