Metadata-Version: 2.4
Name: yt
Version: 4.4.1
Summary: An analysis and visualization toolkit for volumetric data
Author-email: The yt project <yt-dev@python.org>
License: BSD 3-Clause
Project-URL: Homepage, https://yt-project.org/
Project-URL: Documentation, https://yt-project.org/doc/
Project-URL: Source, https://github.com/yt-project/yt/
Project-URL: Tracker, https://github.com/yt-project/yt/issues
Keywords: astronomy astrophysics visualization amr adaptivemeshrefinement
Classifier: Development Status :: 5 - Production/Stable
Classifier: Environment :: Console
Classifier: Framework :: Matplotlib
Classifier: Intended Audience :: Science/Research
Classifier: License :: OSI Approved :: BSD License
Classifier: Operating System :: MacOS :: MacOS X
Classifier: Operating System :: POSIX :: AIX
Classifier: Operating System :: POSIX :: Linux
Classifier: Programming Language :: C
Classifier: Programming Language :: Python :: 3
Classifier: Programming Language :: Python :: 3 :: Only
Classifier: Programming Language :: Python :: 3.10
Classifier: Programming Language :: Python :: 3.11
Classifier: Programming Language :: Python :: 3.12
Classifier: Programming Language :: Python :: 3.13
Classifier: Topic :: Scientific/Engineering :: Astronomy
Classifier: Topic :: Scientific/Engineering :: Physics
Classifier: Topic :: Scientific/Engineering :: Visualization
Requires-Python: >=3.10.4
License-File: COPYING.txt
Requires-Dist: cmyt>=1.1.2
Requires-Dist: ewah-bool-utils>=1.2.0
Requires-Dist: matplotlib>=3.5
Requires-Dist: more-itertools>=8.4
Requires-Dist: numpy<3,>=1.21.3
Requires-Dist: numpy!=2.0.1; platform_machine == "arm64" and platform_system == "Darwin"
Requires-Dist: packaging>=20.9
Requires-Dist: pillow>=8.3.2
Requires-Dist: tomli-w>=0.4.0
Requires-Dist: tqdm>=3.4.0
Requires-Dist: unyt>=2.9.2
Requires-Dist: tomli>=1.2.3; python_version < "3.11"
Requires-Dist: typing-extensions>=4.4.0; python_version < "3.12"
Provides-Extra: hdf5
Requires-Dist: h5py!=3.12.0,>=3.1.0; platform_system == "Windows" and extra == "hdf5"
Provides-Extra: netcdf4
Requires-Dist: netCDF4!=1.6.1,>=1.5.3; extra == "netcdf4"
Provides-Extra: fortran
Requires-Dist: f90nml>=1.1; extra == "fortran"
Provides-Extra: adaptahop
Provides-Extra: ahf
Provides-Extra: amrex
Provides-Extra: amrvac
Requires-Dist: yt[Fortran]; extra == "amrvac"
Provides-Extra: art
Provides-Extra: arepo
Requires-Dist: yt[HDF5]; extra == "arepo"
Provides-Extra: artio
Provides-Extra: athena
Provides-Extra: athena-pp
Provides-Extra: boxlib
Provides-Extra: cf-radial
Requires-Dist: xarray>=0.16.1; extra == "cf-radial"
Requires-Dist: arm-pyart>=1.19.2; extra == "cf-radial"
Provides-Extra: chimera
Requires-Dist: yt[HDF5]; extra == "chimera"
Provides-Extra: chombo
Requires-Dist: yt[HDF5]; extra == "chombo"
Provides-Extra: cholla
Requires-Dist: yt[HDF5]; extra == "cholla"
Provides-Extra: eagle
Requires-Dist: yt[HDF5]; extra == "eagle"
Provides-Extra: enzo-e
Requires-Dist: yt[HDF5]; extra == "enzo-e"
Requires-Dist: libconf>=1.0.1; extra == "enzo-e"
Provides-Extra: enzo
Requires-Dist: yt[HDF5]; extra == "enzo"
Requires-Dist: libconf>=1.0.1; extra == "enzo"
Provides-Extra: exodus-ii
Requires-Dist: yt[netCDF4]; extra == "exodus-ii"
Provides-Extra: fits
Requires-Dist: astropy>=4.0.1; extra == "fits"
Requires-Dist: regions>=0.7; extra == "fits"
Provides-Extra: flash
Requires-Dist: yt[HDF5]; extra == "flash"
Provides-Extra: gadget
Requires-Dist: yt[HDF5]; extra == "gadget"
Provides-Extra: gadget-fof
Requires-Dist: yt[HDF5]; extra == "gadget-fof"
Provides-Extra: gamer
Requires-Dist: yt[HDF5]; extra == "gamer"
Provides-Extra: gdf
Requires-Dist: yt[HDF5]; extra == "gdf"
Provides-Extra: gizmo
Requires-Dist: yt[HDF5]; extra == "gizmo"
Provides-Extra: halo-catalog
Requires-Dist: yt[HDF5]; extra == "halo-catalog"
Provides-Extra: http-stream
Requires-Dist: requests>=2.20.0; extra == "http-stream"
Provides-Extra: idefix
Requires-Dist: yt_idefix[HDF5]>=2.3.0; extra == "idefix"
Provides-Extra: moab
Requires-Dist: yt[HDF5]; extra == "moab"
Provides-Extra: nc4-cm1
Requires-Dist: yt[netCDF4]; extra == "nc4-cm1"
Provides-Extra: open-pmd
Requires-Dist: yt[HDF5]; extra == "open-pmd"
Provides-Extra: owls
Requires-Dist: yt[HDF5]; extra == "owls"
Provides-Extra: owls-subfind
Requires-Dist: yt[HDF5]; extra == "owls-subfind"
Provides-Extra: parthenon
Requires-Dist: yt[HDF5]; extra == "parthenon"
Provides-Extra: ramses
Requires-Dist: yt[Fortran]; extra == "ramses"
Requires-Dist: scipy; extra == "ramses"
Provides-Extra: rockstar
Provides-Extra: sdf
Requires-Dist: requests>=2.20.0; extra == "sdf"
Provides-Extra: stream
Provides-Extra: swift
Requires-Dist: yt[HDF5]; extra == "swift"
Provides-Extra: tipsy
Provides-Extra: ytdata
Requires-Dist: yt[HDF5]; extra == "ytdata"
Provides-Extra: full
Requires-Dist: cartopy>=0.22.0; extra == "full"
Requires-Dist: firefly>=3.2.0; extra == "full"
Requires-Dist: glueviz>=0.13.3; extra == "full"
Requires-Dist: ipython>=7.16.2; extra == "full"
Requires-Dist: ipywidgets>=8.0.0; extra == "full"
Requires-Dist: miniballcpp>=0.2.1; extra == "full"
Requires-Dist: mpi4py>=3.0.3; extra == "full"
Requires-Dist: pandas>=1.1.2; extra == "full"
Requires-Dist: pooch>=0.7.0; extra == "full"
Requires-Dist: pyaml>=17.10.0; extra == "full"
Requires-Dist: pykdtree>=1.3.1; extra == "full"
Requires-Dist: pyx>=0.15; extra == "full"
Requires-Dist: scipy>=1.5.0; extra == "full"
Requires-Dist: glue-core!=1.2.4; python_version >= "3.10" and extra == "full"
Requires-Dist: ratarmount~=0.8.1; (platform_system != "Windows" and platform_system != "Darwin") and extra == "full"
Requires-Dist: yt[adaptahop]; extra == "full"
Requires-Dist: yt[ahf]; extra == "full"
Requires-Dist: yt[amrex]; extra == "full"
Requires-Dist: yt[amrvac]; extra == "full"
Requires-Dist: yt[art]; extra == "full"
Requires-Dist: yt[arepo]; extra == "full"
Requires-Dist: yt[artio]; extra == "full"
Requires-Dist: yt[athena]; extra == "full"
Requires-Dist: yt[athena_pp]; extra == "full"
Requires-Dist: yt[boxlib]; extra == "full"
Requires-Dist: yt[cf_radial]; extra == "full"
Requires-Dist: yt[chimera]; extra == "full"
Requires-Dist: yt[chombo]; extra == "full"
Requires-Dist: yt[cholla]; extra == "full"
Requires-Dist: yt[eagle]; extra == "full"
Requires-Dist: yt[enzo_e]; extra == "full"
Requires-Dist: yt[enzo]; extra == "full"
Requires-Dist: yt[exodus_ii]; extra == "full"
Requires-Dist: yt[fits]; extra == "full"
Requires-Dist: yt[flash]; extra == "full"
Requires-Dist: yt[gadget]; extra == "full"
Requires-Dist: yt[gadget_fof]; extra == "full"
Requires-Dist: yt[gamer]; extra == "full"
Requires-Dist: yt[gdf]; extra == "full"
Requires-Dist: yt[gizmo]; extra == "full"
Requires-Dist: yt[halo_catalog]; extra == "full"
Requires-Dist: yt[http_stream]; extra == "full"
Requires-Dist: yt[idefix]; extra == "full"
Requires-Dist: yt[moab]; extra == "full"
Requires-Dist: yt[nc4_cm1]; extra == "full"
Requires-Dist: yt[open_pmd]; extra == "full"
Requires-Dist: yt[owls]; extra == "full"
Requires-Dist: yt[owls_subfind]; extra == "full"
Requires-Dist: yt[parthenon]; extra == "full"
Requires-Dist: yt[ramses]; extra == "full"
Requires-Dist: yt[rockstar]; extra == "full"
Requires-Dist: yt[sdf]; extra == "full"
Requires-Dist: yt[stream]; extra == "full"
Requires-Dist: yt[swift]; extra == "full"
Requires-Dist: yt[tipsy]; extra == "full"
Requires-Dist: yt[ytdata]; extra == "full"
Provides-Extra: mapserver
Requires-Dist: bottle; extra == "mapserver"
Provides-Extra: test
Requires-Dist: pyaml>=17.10.0; extra == "test"
Requires-Dist: pytest>=6.1; extra == "test"
Requires-Dist: pytest-mpl>=0.16.1; extra == "test"
Requires-Dist: sympy!=1.10,!=1.9; extra == "test"
Requires-Dist: imageio!=2.35.0; extra == "test"
Requires-Dist: contourpy; extra == "test"
Dynamic: license-file
